CHANGES.txt
MANIFEST.in
README.txt
setup.py
slapos/__init__.py
slapos.package.egg-info/PKG-INFO
slapos.package.egg-info/SOURCES.txt
slapos.package.egg-info/dependency_links.txt
slapos.package.egg-info/entry_points.txt
slapos.package.egg-info/namespace_packages.txt
slapos.package.egg-info/not-zip-safe
slapos.package.egg-info/requires.txt
slapos.package.egg-info/top_level.txt
slapos/package/__init__.py
slapos/package/autoupdate.py
slapos/package/base_promise.py
slapos/package/conf.py
slapos/package/distribution.py
slapos/package/signature.py
slapos/package/tester.py
slapos/package/update.py
slapos/package/upload_key.py
slapos/package/promise/__init__.py
slapos/package/promise/core.py
slapos/package/promise/hostname.py
slapos/package/promise/limits.py
slapos/package/promise/slappkgcron.py
slapos/package/promise/template/limits.conf.in
slapos/package/template/__init__.py
slapos/package/template/update.cfg.in
slapos/package/template/update.cron.in
slapos/package/test/__init__.py
slapos/package/test/base.py
slapos/package/test/test_base_promise.py
slapos/package/test/test_distribution.py
slapos/package/test/test_promise_core.py
slapos/package/test/test_promise_hostname.py
slapos/package/test/test_promise_limit.py
slapos/package/test/test_signature.py