Metadata-Version: 1.1
Name: slapos.package
Version: 0.2.1.1
Summary: SlapOS Package Utils
Home-page: http://www.slapos.org
Author: VIFIB
Author-email: UNKNOWN
License: GPLv3
Keywords: slapos package update
Platform: UNKNOWN
Classifier: Programming Language :: Python
